{
  "hadm_id": 27487226,
  "subject_id": 10014354,
  "gender": "M",
  "age": 60,
  "admission_type": "URGENT",
  "chief_complaint": "Abdominal pain",
  "history": "Patient is a 60 year old m.\n\nChief Complaint: Abdominal pain\n\nAdmission Type: URGENT\n\nRecent Lab Results:\nRDW: 14.9 %\nMagnesium: 2.1 mg/dL\nPT: 12.5 sec\nUrea Nitrogen: 35.0 mg/dL\nCreatinine: 1.7 mg/dL\nINR(PT): 1.2 nan\nGlucose: 194.0 mg/dL\nPotassium: 5.7 mEq/L\nAnion Gap: 14.0 mEq/L\nBands: 1.0 %\n\nCurrent Medications:\nMultivitamins 1TAB\nNeutra-Phos 1PKT\nVial 1VIAL\nAspirin 81mg\nBag 1BAG\nCloNIDine 0.1mg\nColchicine 0.6mg\nLisinopril 5mg\nOxyCODONE (Immediate Release) 5mg\nOxyCODONE (Immediate Release) 5mg\n",
  "diagnosis_icd": "J189",
  "diagnosis_name": "Pneumonia, unspecified organism",
  "lab_events_count": 929,
  "microbiology_count": 10,
  "medication_count": 164,
  "procedure_codes": [
    "0W9D30Z"
  ]
}